vocab/__init__.py
vocab/lib/__init__.py
vocab/lib/app.py
vocab/lib/config.py
vocab/lib/clilib/__init__.py
vocab/lib/clilib/charDef.py
vocab/lib/clilib/client.py
vocab/lib/clilib/utils.py
vocabs-1.0.0.data/scripts/vocab
vocabs-1.0.0.dist-info/DESCRIPTION.rst
vocabs-1.0.0.dist-info/METADATA
vocabs-1.0.0.dist-info/RECORD
vocabs-1.0.0.dist-info/WHEEL
vocabs-1.0.0.dist-info/metadata.json
vocabs-1.0.0.dist-info/top_level.txt
