Metadata-Version: 2.0
Name: vocabs
Version: 1.0.0
Summary: A lightweight online dictionary integration to the command line.
Home-page: https://github.com/Mckinsey666/Vocab
Author: Mckinsey666
Author-email: UNKNOWN
License: MIT
Keywords: cli english words dictionary vocabulary
Platform: UNKNOWN
